setup.cfg
setup.py
pyprot/__init__.py
pyprot.egg-info/PKG-INFO
pyprot.egg-info/SOURCES.txt
pyprot.egg-info/dependency_links.txt
pyprot.egg-info/requires.txt
pyprot.egg-info/top_level.txt
pyprot/align/__init__.py
pyprot/align/align.py
pyprot/align/blosum.py
pyprot/align/score.py
pyprot/base/__init__.py
pyprot/base/aminoacid.py
pyprot/base/sequence.py
pyprot/base/test/__init__.py
pyprot/base/test/test_aminoacid.py
pyprot/base/test/test_sequence.py
pyprot/data/__init__.py
pyprot/data/dssp.py
pyprot/data/fasta.py
pyprot/structure/__init__.py
pyprot/structure/gor.py