Metadata-Version: 1.1
Name: pyprot
Version: 0.1-alpha
Summary: Python Proteins
Home-page: https://github.com/StanIsAdmin/PyProt
Author: Stanislas Gueniffey
Author-email: gueniffeystanislas@gmail.com
License: GPL-3.0
Download-URL: https://github.com/StanIsAdmin/PyProt/archive/0.1-alpha.tar.gz
Keywords: biology proteins sequence-alignment
Platform: UNKNOWN
Classifier: Development Status :: 3 - Alpha
Classifier: Intended Audience :: Developers
Classifier: Intended Audience :: Education
Classifier: Intended Audience :: Science/Research
Classifier: License :: OSI Approved :: GNU General Public License v3 (GPLv3)
Classifier: Natural Language :: English
Classifier: Programming Language :: Python :: 3 :: Only
Classifier: Programming Language :: Python :: 3.3
Classifier: Programming Language :: Python :: 3.4
Classifier: Programming Language :: Python :: 3.5
Classifier: Topic :: Scientific/Engineering :: Bio-Informatics
